mnistlib/__init__.py
mnistlib-0.0.18.dist-info/METADATA
mnistlib-0.0.18.dist-info/WHEEL
mnistlib-0.0.18.dist-info/top_level.txt
mnistlib-0.0.18.dist-info/RECORD
