Metadata-Version: 2.1
Name: mnistlib
Version: 0.0.18
Summary: geometric transformations for mnist dataset
Home-page: UNKNOWN
Author: Oleg Zyablov
Author-email: oleg.z98@mail.ru
License: MIT
Keywords: mnist
Platform: UNKNOWN
Requires-Dist: mnist
Requires-Dist: matplotlib
Requires-Dist: Pillow
Requires-Dist: numpy
